{
  "predictions": [
    {
      "user": "Lajos ",
      "matchId": 10,
      "scoreA": 5,
      "scoreB": 0,
      "advancer": null
    },
    {
      "user": "Lajos ",
      "matchId": 9,
      "scoreA": 1,
      "scoreB": 1,
      "advancer": null
    },
    {
      "user": "Lajos ",
      "matchId": 11,
      "scoreA": 2,
      "scoreB": 2,
      "advancer": null
    },
    {
      "user": "Lajos ",
      "matchId": 12,
      "scoreA": 3,
      "scoreB": 1,
      "advancer": null
    },
    {
      "user": "Lajos ",
      "matchId": 13,
      "scoreA": 1,
      "scoreB": 1,
      "advancer": null
    },
    {
      "user": "Lajos ",
      "matchId": 14,
      "scoreA": 5,
      "scoreB": 0,
      "advancer": null
    },
    {
      "user": "Lajos ",
      "matchId": 15,
      "scoreA": 1,
      "scoreB": 1,
      "advancer": null
    },
    {
      "user": "Lajos ",
      "matchId": 16,
      "scoreA": 1,
      "scoreB": 3,
      "advancer": null
    },
    {
      "user": "Lajos ",
      "matchId": 17,
      "scoreA": 2,
      "scoreB": 1,
      "advancer": null
    },
    {
      "user": "Lajos ",
      "matchId": 18,
      "scoreA": 1,
      "scoreB": 4,
      "advancer": null
    },
    {
      "user": "Lajos ",
      "matchId": 19,
      "scoreA": 2,
      "scoreB": 0,
      "advancer": null
    },
    {
      "user": "Lajos ",
      "matchId": 20,
      "scoreA": 3,
      "scoreB": 1,
      "advancer": null
    },
    {
      "user": "Lajos ",
      "matchId": 21,
      "scoreA": 3,
      "scoreB": 0,
      "advancer": null
    },
    {
      "user": "Lajos ",
      "matchId": 22,
      "scoreA": 1,
      "scoreB": 1,
      "advancer": null
    },
    {
      "user": "Lajos ",
      "matchId": 23,
      "scoreA": 0,
      "scoreB": 2,
      "advancer": null
    },
    {
      "user": "Lajos ",
      "matchId": 24,
      "scoreA": 2,
      "scoreB": 0,
      "advancer": null
    },
    {
      "user": "Lajos ",
      "matchId": 25,
      "scoreA": 1,
      "scoreB": 1,
      "advancer": null
    },
    {
      "user": "Lajos ",
      "matchId": 26,
      "scoreA": 3,
      "scoreB": 0,
      "advancer": null
    },
    {
      "user": "Lajos ",
      "matchId": 27,
      "scoreA": 4,
      "scoreB": 0,
      "advancer": null
    },
    {
      "user": "Lajos ",
      "matchId": 28,
      "scoreA": 1,
      "scoreB": 2,
      "advancer": null
    },
    {
      "user": "Lajos ",
      "matchId": 29,
      "scoreA": 4,
      "scoreB": 0,
      "advancer": null
    },
    {
      "user": "Lajos ",
      "matchId": 30,
      "scoreA": 1,
      "scoreB": 1,
      "advancer": null
    },
    {
      "user": "Lajos ",
      "matchId": 31,
      "scoreA": 3,
      "scoreB": 1,
      "advancer": null
    },
    {
      "user": "Lajos ",
      "matchId": 32,
      "scoreA": 2,
      "scoreB": 1,
      "advancer": null
    },
    {
      "user": "Lajos ",
      "matchId": 33,
      "scoreA": 3,
      "scoreB": 1,
      "advancer": null
    },
    {
      "user": "Lajos ",
      "matchId": 34,
      "scoreA": 3,
      "scoreB": 0,
      "advancer": null
    },
    {
      "user": "Lajos ",
      "matchId": 35,
      "scoreA": 3,
      "scoreB": 1,
      "advancer": null
    },
    {
      "user": "Lajos ",
      "matchId": 36,
      "scoreA": 1,
      "scoreB": 2,
      "advancer": null
    },
    {
      "user": "Lajos ",
      "matchId": 37,
      "scoreA": 3,
      "scoreB": 0,
      "advancer": null
    },
    {
      "user": "Lajos ",
      "matchId": 38,
      "scoreA": 0,
      "scoreB": 2,
      "advancer": null
    },
    {
      "user": "Lajos ",
      "matchId": 39,
      "scoreA": 3,
      "scoreB": 0,
      "advancer": null
    },
    {
      "user": "Lajos ",
      "matchId": 40,
      "scoreA": 4,
      "scoreB": 0,
      "advancer": null
    },
    {
      "user": "Lajos ",
      "matchId": 41,
      "scoreA": 3,
      "scoreB": 0,
      "advancer": null
    },
    {
      "user": "Lajos ",
      "matchId": 42,
      "scoreA": 3,
      "scoreB": 2,
      "advancer": null
    },
    {
      "user": "Lajos ",
      "matchId": 43,
      "scoreA": 3,
      "scoreB": 0,
      "advancer": null
    },
    {
      "user": "Lajos ",
      "matchId": 44,
      "scoreA": 0,
      "scoreB": 2,
      "advancer": null
    },
    {
      "user": "Lajos ",
      "matchId": 45,
      "scoreA": 4,
      "scoreB": 0,
      "advancer": null
    },
    {
      "user": "Lajos ",
      "matchId": 46,
      "scoreA": 0,
      "scoreB": 3,
      "advancer": null
    },
    {
      "user": "Lajos ",
      "matchId": 47,
      "scoreA": 2,
      "scoreB": 1,
      "advancer": null
    },
    {
      "user": "Lajos ",
      "matchId": 48,
      "scoreA": 2,
      "scoreB": 0,
      "advancer": null
    },
    {
      "user": "Lajos ",
      "matchId": 49,
      "scoreA": 1,
      "scoreB": 3,
      "advancer": null
    },
    {
      "user": "Lajos ",
      "matchId": 50,
      "scoreA": 4,
      "scoreB": 0,
      "advancer": null
    },
    {
      "user": "Lajos ",
      "matchId": 51,
      "scoreA": 1,
      "scoreB": 2,
      "advancer": null
    },
    {
      "user": "Lajos ",
      "matchId": 52,
      "scoreA": 0,
      "scoreB": 2,
      "advancer": null
    },
    {
      "user": "Lajos ",
      "matchId": 53,
      "scoreA": 2,
      "scoreB": 0,
      "advancer": null
    },
    {
      "user": "Lajos ",
      "matchId": 54,
      "scoreA": 2,
      "scoreB": 1,
      "advancer": null
    },
    {
      "user": "Lajos ",
      "matchId": 55,
      "scoreA": 0,
      "scoreB": 2,
      "advancer": null
    },
    {
      "user": "Lajos ",
      "matchId": 56,
      "scoreA": 1,
      "scoreB": 3,
      "advancer": null
    },
    {
      "user": "Lajos ",
      "matchId": 57,
      "scoreA": 1,
      "scoreB": 3,
      "advancer": null
    },
    {
      "user": "Lajos ",
      "matchId": 58,
      "scoreA": 2,
      "scoreB": 2,
      "advancer": null
    },
    {
      "user": "Lajos ",
      "matchId": 59,
      "scoreA": 1,
      "scoreB": 1,
      "advancer": null
    },
    {
      "user": "Lajos ",
      "matchId": 60,
      "scoreA": 1,
      "scoreB": 4,
      "advancer": null
    },
    {
      "user": "Lajos ",
      "matchId": 61,
      "scoreA": 2,
      "scoreB": 1,
      "advancer": null
    },
    {
      "user": "Lajos ",
      "matchId": 62,
      "scoreA": 1,
      "scoreB": 1,
      "advancer": null
    },
    {
      "user": "Lajos ",
      "matchId": 63,
      "scoreA": 2,
      "scoreB": 0,
      "advancer": null
    },
    {
      "user": "Lajos ",
      "matchId": 64,
      "scoreA": 0,
      "scoreB": 3,
      "advancer": null
    },
    {
      "user": "Lajos ",
      "matchId": 65,
      "scoreA": 1,
      "scoreB": 3,
      "advancer": null
    },
    {
      "user": "Lajos ",
      "matchId": 66,
      "scoreA": 1,
      "scoreB": 3,
      "advancer": null
    },
    {
      "user": "Lajos ",
      "matchId": 67,
      "scoreA": 0,
      "scoreB": 4,
      "advancer": null
    },
    {
      "user": "Lajos ",
      "matchId": 68,
      "scoreA": 2,
      "scoreB": 0,
      "advancer": null
    },
    {
      "user": "Lajos ",
      "matchId": 69,
      "scoreA": 2,
      "scoreB": 2,
      "advancer": null
    },
    {
      "user": "Lajos ",
      "matchId": 70,
      "scoreA": 0,
      "scoreB": 4,
      "advancer": null
    },
    {
      "user": "Lajos ",
      "matchId": 71,
      "scoreA": 1,
      "scoreB": 3,
      "advancer": null
    },
    {
      "user": "Lajos ",
      "matchId": 72,
      "scoreA": 2,
      "scoreB": 0,
      "advancer": null
    },
    {
      "user": "Lajos",
      "matchId": 73,
      "scoreA": 1,
      "scoreB": 3,
      "advancer": "B"
    },
    {
      "user": "Lajos",
      "matchId": 74,
      "scoreA": 3,
      "scoreB": 1,
      "advancer": "A"
    },
    {
      "user": "Lajos",
      "matchId": 75,
      "scoreA": 2,
      "scoreB": 1,
      "advancer": "A"
    },
    {
      "user": "Lajos",
      "matchId": 76,
      "scoreA": 3,
      "scoreB": 2,
      "advancer": "A"
    },
    {
      "user": "Lajos",
      "matchId": 77,
      "scoreA": 4,
      "scoreB": 0,
      "advancer": "A"
    },
    {
      "user": "Lajos",
      "matchId": 78,
      "scoreA": 2,
      "scoreB": 2,
      "advancer": "B"
    },
    {
      "user": "Lajos",
      "matchId": 79,
      "scoreA": 3,
      "scoreB": 1,
      "advancer": "A"
    },
    {
      "user": "Lajos",
      "matchId": 80,
      "scoreA": 2,
      "scoreB": 0,
      "advancer": "A"
    },
    {
      "user": "Lajos",
      "matchId": 81,
      "scoreA": 3,
      "scoreB": 1,
      "advancer": "A"
    },
    {
      "user": "Lajos",
      "matchId": 82,
      "scoreA": 1,
      "scoreB": 2,
      "advancer": "B"
    },
    {
      "user": "Lajos",
      "matchId": 83,
      "scoreA": 2,
      "scoreB": 2,
      "advancer": "B"
    },
    {
      "user": "Lajos",
      "matchId": 84,
      "scoreA": 4,
      "scoreB": 2,
      "advancer": "A"
    },
    {
      "user": "Lajos",
      "matchId": 85,
      "scoreA": 3,
      "scoreB": 1,
      "advancer": "A"
    },
    {
      "user": "Lajos",
      "matchId": 86,
      "scoreA": 2,
      "scoreB": 1,
      "advancer": "A"
    },
    {
      "user": "Lajos",
      "matchId": 87,
      "scoreA": 1,
      "scoreB": 1,
      "advancer": "B"
    },
    {
      "user": "Lajos",
      "matchId": 88,
      "scoreA": 3,
      "scoreB": 1,
      "advancer": "A"
    },
    {
      "user": "Lajos ",
      "matchId": 89,
      "scoreA": 1,
      "scoreB": 1,
      "advancer": "B"
    },
    {
      "user": "Lajos ",
      "matchId": 90,
      "scoreA": 1,
      "scoreB": 2,
      "advancer": "B"
    },
    {
      "user": "Lajos ",
      "matchId": 91,
      "scoreA": 3,
      "scoreB": 2,
      "advancer": "A"
    },
    {
      "user": "Lajos ",
      "matchId": 92,
      "scoreA": 2,
      "scoreB": 1,
      "advancer": "A"
    },
    {
      "user": "Lajos ",
      "matchId": 93,
      "scoreA": 1,
      "scoreB": 2,
      "advancer": "B"
    },
    {
      "user": "Lajos ",
      "matchId": 94,
      "scoreA": 2,
      "scoreB": 1,
      "advancer": "A"
    },
    {
      "user": "Lajos ",
      "matchId": 95,
      "scoreA": 3,
      "scoreB": 0,
      "advancer": "A"
    },
    {
      "user": "Lajos ",
      "matchId": 96,
      "scoreA": 1,
      "scoreB": 1,
      "advancer": "A"
    },
    {
      "user": "Lajos ",
      "matchId": 97,
      "scoreA": 1,
      "scoreB": 2,
      "advancer": "B"
    },
    {
      "user": "Lajos ",
      "matchId": 98,
      "scoreA": 3,
      "scoreB": 2,
      "advancer": "A"
    },
    {
      "user": "Lajos ",
      "matchId": 99,
      "scoreA": 2,
      "scoreB": 2,
      "advancer": "A"
    },
    {
      "user": "Lajos ",
      "matchId": 100,
      "scoreA": 1,
      "scoreB": 1,
      "advancer": "B"
    },
    {
"user": "Lajos ",
"matchId": 101,
"scoreA": 2,
"scoreB": 2,
"advancer": "B"
},
{
"user": "Lajos ",
"matchId": 102,
"scoreA": 2,
"scoreB": 2,
"advancer": "B"
},
    {
"user": "Lajos ",
"matchId": 103,
"scoreA": 3,
"scoreB": 3,
"advancer": "B"
},
{
"user": "Lajos ",
"matchId": 104,
"scoreA": 1,
"scoreB": 1,
"advancer": "A"
}
  ]
}
